{"id":"3e65782f-7376-49bf-948f-05f09bd6c63d","companyId":1110420,"type":"WORK_CARRIED","status":"PUBLISHED","title":"Restore lights to house.  Mains were repeatedly tripping","review":"5 star!  Excellent service.  Very polite, understanding and helpful.  Will definitely be recommending to all","createdAt":"2022-10-28T15:56:24.907Z","updatedAt":"2023-01-18T11:37:05.000Z","legacyId":"aIe66Q7CGPStjhqdGgBT","consumerId":"","categoryId":12,"topLevelCategoryId":12,"location":{"postcode":"M24"},"verified":"NOT_VERIFIED","rating":{"qualityOfWorkmanship":10,"tidiness":10,"reliabilityAndTimekeeping":10,"courtesy":10,"rating":10},"publishedAt":"2022-10-28T15:58:06.000Z","name":"Renegade Electrical Ltd","uniqueName":"renegadeelectrical"}
